python_errorhandler/__init__.py
python_errorhandler-2.1.0.dist-info/METADATA
python_errorhandler-2.1.0.dist-info/WHEEL
python_errorhandler-2.1.0.dist-info/top_level.txt
python_errorhandler-2.1.0.dist-info/RECORD
