Metadata-Version: 2.1
Name: python-errorhandler
Version: 2.1.0
Summary: This Python package, 'python_errorhandler', simplifies error handling in your code. You no longer need to write try-catch blocks for every function. Instead, you can import this package and use the included decorator with your functions.    The decorator allows you to specify a custom error message for better error handling and debugging.
Home-page: https://github.com/nimesh-p/python_error_handler
Author: Nimesh Prajapati
Author-email: prajapatin953@gmail.com
License: MIT License
Requires-Dist: Django
Requires-Dist: djangorestframework
